sphinxcontrib_chapeldomain-0.0.39-py3.13-nspkg.pth
sphinxcontrib/chapeldomain/__init__.py
sphinxcontrib/chapeldomain/chapel.py
sphinxcontrib_chapeldomain-0.0.39.dist-info/licenses/LICENSE
sphinxcontrib_chapeldomain-0.0.39.dist-info/METADATA
sphinxcontrib_chapeldomain-0.0.39.dist-info/WHEEL
sphinxcontrib_chapeldomain-0.0.39.dist-info/namespace_packages.txt
sphinxcontrib_chapeldomain-0.0.39.dist-info/top_level.txt
sphinxcontrib_chapeldomain-0.0.39.dist-info/RECORD
