Metadata-Version: 2.4
Name: sphinxcontrib-chapeldomain
Version: 0.0.39
Summary: Chapel domain for Sphinx
Home-page: https://github.com/chapel-lang/sphinxcontrib-chapeldomain
Download-URL: https://pypi.python.org/pypi/sphinxcontrib-chapeldomain
Author: Chapel Team
Author-email: chapel+developers@discoursemail.com
License: Apache License v2.0
Platform: any
Classifier: Development Status :: 3 - Alpha
Classifier: Environment :: Console
Classifier: Environment :: Web Environment
Classifier: Intended Audience :: Developers
Classifier: Intended Audience :: Education
Classifier: License :: OSI Approved :: Apache Software License
Classifier: Operating System :: OS Independent
Classifier: Programming Language :: Python
Classifier: Programming Language :: Python :: 3
Classifier: Framework :: Sphinx :: Domain
Classifier: Framework :: Sphinx :: Extension
Classifier: Topic :: Documentation
Classifier: Topic :: Documentation :: Sphinx
Classifier: Topic :: Text Processing
Classifier: Topic :: Utilities
License-File: LICENSE
Requires-Dist: docutils==0.21.2
Requires-Dist: Sphinx==8.1.3
Dynamic: author
Dynamic: author-email
Dynamic: classifier
Dynamic: description
Dynamic: download-url
Dynamic: home-page
Dynamic: license
Dynamic: license-file
Dynamic: platform
Dynamic: requires-dist
Dynamic: summary
